InstagramBOT/__init__.py
InstagramBOT/core.py
InstagramBOT-1.0.0.dist-info/LICENSE
InstagramBOT-1.0.0.dist-info/METADATA
InstagramBOT-1.0.0.dist-info/WHEEL
InstagramBOT-1.0.0.dist-info/top_level.txt
InstagramBOT-1.0.0.dist-info/RECORD
